CHANGES.txt
LICENSE.txt
MANIFEST.in
README.txt
setup.py
js/__init__.py
js.angular_preventdefault.egg-info/PKG-INFO
js.angular_preventdefault.egg-info/SOURCES.txt
js.angular_preventdefault.egg-info/dependency_links.txt
js.angular_preventdefault.egg-info/entry_points.txt
js.angular_preventdefault.egg-info/namespace_packages.txt
js.angular_preventdefault.egg-info/not-zip-safe
js.angular_preventdefault.egg-info/requires.txt
js.angular_preventdefault.egg-info/top_level.txt
js/angular_preventdefault/__init__.py
js/angular_preventdefault/test_angular-prevent-default.txt
js/angular_preventdefault/resources/angular-prevent-default.js