Metadata-Version: 1.0
Name: js.angular-preventdefault
Version: 1.0.3-1
Summary: Fanstatic packaging of angular-prevent-default
Home-page: UNKNOWN
Author: Fanstatic Developers
Author-email: fanstatic@googlegroups.com
License: BSD
Platform: UNKNOWN
